pivcrypt/__init__.py
pivcrypt/__main__.py
pivcrypt/fido_applet.py
pivcrypt-1.0.0.dist-info/LICENSE
pivcrypt-1.0.0.dist-info/METADATA
pivcrypt-1.0.0.dist-info/WHEEL
pivcrypt-1.0.0.dist-info/entry_points.txt
pivcrypt-1.0.0.dist-info/top_level.txt
pivcrypt-1.0.0.dist-info/RECORD
