Metadata-Version: 2.1
Name: pivcrypt
Version: 1.0.0
Summary: File encryption using PIV applet
Home-page: https://crayonic.io
Author: Crayonic B.V.
Author-email: support@crayonic.io
License: UNKNOWN
Platform: UNKNOWN
Classifier: Programming Language :: Python :: 3
Classifier: License :: OSI Approved :: MIT License
Classifier: Operating System :: OS Independent
Requires-Python: >=3.6
License-File: LICENSE
Requires-Dist: cffi (==1.14.6)
Requires-Dist: click (==8.0.1)
Requires-Dist: colorama (==0.4.4)
Requires-Dist: cryptography (==3.4.8)
Requires-Dist: pycparser (==2.20)
Requires-Dist: pyscard (==2.0.2)
